duckdb_engine/.hypothesis/examples/f024fc7dfe5f1878/7210af19145ec2a8
duckdb_engine/.hypothesis/examples/f024fc7dfe5f1878/bec021b4f368e306
duckdb_engine/.hypothesis/unicode_data/12.1.0/charmap.json.gz
duckdb_engine/__init__.py
duckdb_engine/_supports.py
duckdb_engine/config.py
duckdb_engine/conftest.py
duckdb_engine/datatypes.py
duckdb_engine/py.typed
duckdb_engine/tests/__init__.py
duckdb_engine/tests/conftest.py
duckdb_engine/tests/snapshots/__init__.py
duckdb_engine/tests/snapshots/snap_test_basic.py
duckdb_engine/tests/test_basic.py
duckdb_engine/tests/test_datatypes.py
duckdb_engine/tests/test_integration.py
duckdb_engine/tests/test_pandas.py
duckdb_engine/tests/test_pyarrow.py
duckdb_engine/tests/util.py
duckdb_engine-0.15.1.dist-info/LICENSE.txt
duckdb_engine-0.15.1.dist-info/METADATA
duckdb_engine-0.15.1.dist-info/WHEEL
duckdb_engine-0.15.1.dist-info/entry_points.txt
duckdb_engine-0.15.1.dist-info/RECORD
