Metadata-Version: 2.3
Name: duckdb_engine
Version: 0.15.1
Summary: SQLAlchemy driver for duckdb
License: MIT
Author: Elliana
Author-email: me@mause.me
Requires-Python: >=3.8,<4
Classifier: License :: OSI Approved :: MIT License
Classifier: Programming Language :: Python :: 3
Classifier: Programming Language :: Python :: 3.8
Classifier: Programming Language :: Python :: 3.9
Classifier: Programming Language :: Python :: 3.10
Classifier: Programming Language :: Python :: 3.11
Classifier: Programming Language :: Python :: 3.12
Classifier: Programming Language :: Python :: 3.13
Requires-Dist: duckdb (>=0.5.0)
Requires-Dist: packaging (>=21)
Requires-Dist: sqlalchemy (>=1.3.22)
Project-URL: Bug Tracker, https://github.com/Mause/duckdb_engine/issues
Project-URL: Changelog, https://github.com/Mause/duckdb_engine/releases
Project-URL: Repository, https://github.com/Mause/duckdb_engine
